setup.py
wikipedia_template_parser/__init__.py
wikipedia_template_parser.egg-info/PKG-INFO
wikipedia_template_parser.egg-info/SOURCES.txt
wikipedia_template_parser.egg-info/dependency_links.txt
wikipedia_template_parser.egg-info/requires.txt
wikipedia_template_parser.egg-info/top_level.txt