Metadata-Version: 1.1
Name: wikipedia-template-parser
Version: 0.1
Summary: Simple library for extracting data from Wikipedia templates
Home-page: https://github.com/SpazioDati/Wikipedia-Template-Parser
Author: Federico Scrinzi
Author-email: scrinzi@spaziodati.eu
License: MIT
Platform: UNKNOWN
Classifier: Development Status :: 3 - Alpha
Classifier: Intended Audience :: Developers
Classifier: Topic :: Software Development :: Libraries
Classifier: Topic :: Internet
Classifier: License :: OSI Approved :: MIT License
Classifier: Programming Language :: Python
Classifier: Programming Language :: Python :: 2.7
